ireadlogs/__init__.py
ireadlogs/__main__.py
ireadlogs/logline.py
ireadlogs/parser.py
ireadlogs/runconfig.py
ireadlogs/stats.py
ireadlogs-0.0.12.dist-info/LICENSE
ireadlogs-0.0.12.dist-info/METADATA
ireadlogs-0.0.12.dist-info/WHEEL
ireadlogs-0.0.12.dist-info/entry_points.txt
ireadlogs-0.0.12.dist-info/top_level.txt
ireadlogs-0.0.12.dist-info/RECORD
