Metadata-Version: 2.1
Name: ireadlogs
Version: 0.0.12
Summary: Small NASA FTP logs analyzer
Home-page: https://github.com/zerogvt/ireadlogs
Author: vas
Author-email: william.gkou@gmail.com
License: UNKNOWN
Project-URL: Bug Tracker, https://github.com/zerogvt/ireadlogs/issues
Platform: UNKNOWN
Classifier: Programming Language :: Python :: 3
Classifier: License :: OSI Approved :: GNU General Public License v2 (GPLv2)
Classifier: Operating System :: OS Independent
Requires-Python: >=3.6
License-File: LICENSE
